workers_control/core/__init__.py
workers_control/core/accountant_notifications.py
workers_control/core/anonymization.py
workers_control/core/control_thresholds.py
workers_control/core/datetime_service.py
workers_control/core/decimal.py
workers_control/core/email.py
workers_control/core/email_notifications.py
workers_control/core/injector.py
workers_control/core/password_hasher.py
workers_control/core/records.py
workers_control/core/repositories.py
workers_control/core/transfers.py
workers_control/core/interactors/__init__.py
workers_control/core/interactors/accept_cooperation.py
workers_control/core/interactors/accept_coordination_transfer.py
workers_control/core/interactors/answer_company_work_invite.py
workers_control/core/interactors/approve_plan.py
workers_control/core/interactors/cancel_cooperation_solicitation.py
workers_control/core/interactors/change_user_email_address.py
workers_control/core/interactors/change_user_password.py
workers_control/core/interactors/confirm_company.py
workers_control/core/interactors/confirm_member.py
workers_control/core/interactors/create_cooperation.py
workers_control/core/interactors/create_draft_from_plan.py
workers_control/core/interactors/create_plan_draft.py
workers_control/core/interactors/delete_draft.py
workers_control/core/interactors/deny_cooperation.py
workers_control/core/interactors/edit_draft.py
workers_control/core/interactors/end_cooperation.py
workers_control/core/interactors/file_plan_with_accounting.py
workers_control/core/interactors/get_accountant_dashboard.py
workers_control/core/interactors/get_company_dashboard.py
workers_control/core/interactors/get_company_summary.py
workers_control/core/interactors/get_coop_summary.py
workers_control/core/interactors/get_coordination_transfer_request_details.py
workers_control/core/interactors/get_draft_details.py
workers_control/core/interactors/get_member_dashboard.py
workers_control/core/interactors/get_plan_details.py
workers_control-0.1.4.dist-info/licenses/LICENSE
workers_control-0.1.4.dist-info/METADATA
workers_control-0.1.4.dist-info/WHEEL
workers_control-0.1.4.dist-info/top_level.txt
workers_control-0.1.4.dist-info/RECORD
