Metadata-Version: 2.4
Name: workers-control
Version: 0.1.4
Summary: A flask app for labour time accounting.
License-Expression: AGPL-3.0-or-later
Project-URL: Source, https://github.com/ida-arbeitszeit/workers-control
Project-URL: Documentation, https://workers-control.readthedocs.io/
Project-URL: Changelog, https://github.com/ida-arbeitszeit/workers-control/blob/master/CHANGELOG.md
Classifier: Framework :: Flask
Classifier: Programming Language :: Python :: 3
Classifier: Programming Language :: Python :: 3.12
Classifier: Programming Language :: Python :: 3.13
Requires-Python: >=3.12
License-File: LICENSE
Requires-Dist: alembic<=1.17.2,>=1.16.4
Requires-Dist: email-validator==2.2.0
Requires-Dist: flask==3.1.2
Requires-Dist: flask-babel==4.0.0
Requires-Dist: flask-mail==0.10.0
Requires-Dist: flask-talisman==1.1.0
Requires-Dist: flask-login==0.6.3
Requires-Dist: flask-wtf==1.2.2
Requires-Dist: matplotlib==3.10.5
Provides-Extra: profiling
Requires-Dist: flask_profiler; extra == "profiling"
Dynamic: license-file
